{
  "id": "b2b407f7-b7d3-4e3e-a6e2-b2f7f5dc2c5f",
  "name": "EventNest - Local",
  "values": [
    {
      "key": "springBaseUrl",
      "value": "http://localhost:8080/api",
      "type": "default",
      "enabled": true
    },
    {
      "key": "nodeBaseUrl",
      "value": "http://localhost:4000/api",
      "type": "default",
      "enabled": true
    },
    {
      "key": "reportsBaseUrl",
      "value": "http://localhost:5107/api/reports",
      "type": "default",
      "enabled": true
    },
    {
      "key": "adminApiKey",
      "value": "change-me-reporting-admin-key",
      "type": "secret",
      "enabled": true
    },
    {
      "key": "adminEmail",
      "value": "admin@eventnest.io",
      "type": "default",
      "enabled": true
    },
    {
      "key": "adminPassword",
      "value": "Admin@123",
      "type": "secret",
      "enabled": true
    },
    {
      "key": "organizerEmail",
      "value": "organizer@eventnest.io",
      "type": "default",
      "enabled": true
    },
    {
      "key": "organizerPassword",
      "value": "Organizer@123",
      "type": "secret",
      "enabled": true
    },
    {
      "key": "customerEmail",
      "value": "customer@eventnest.io",
      "type": "default",
      "enabled": true
    },
    {
      "key": "customerPassword",
      "value": "Customer@123",
      "type": "secret",
      "enabled": true
    },
    {
      "key": "newUserEmail",
      "value": "",
      "type": "default",
      "enabled": true
    },
    {
      "key": "newUserPassword",
      "value": "Postman@123",
      "type": "secret",
      "enabled": true
    },
    {
      "key": "adminToken",
      "value": "",
      "type": "secret",
      "enabled": true
    },
    {
      "key": "organizerToken",
      "value": "",
      "type": "secret",
      "enabled": true
    },
    {
      "key": "customerToken",
      "value": "",
      "type": "secret",
      "enabled": true
    },
    {
      "key": "newUserToken",
      "value": "",
      "type": "secret",
      "enabled": true
    },
    {
      "key": "adminUserId",
      "value": "",
      "type": "default",
      "enabled": true
    },
    {
      "key": "organizerUserId",
      "value": "",
      "type": "default",
      "enabled": true
    },
    {
      "key": "customerUserId",
      "value": "",
      "type": "default",
      "enabled": true
    },
    {
      "key": "newUserId",
      "value": "",
      "type": "default",
      "enabled": true
    },
    {
      "key": "targetUserId",
      "value": "",
      "type": "default",
      "enabled": true
    },
    {
      "key": "venueId",
      "value": "",
      "type": "default",
      "enabled": true
    },
    {
      "key": "eventId",
      "value": "",
      "type": "default",
      "enabled": true
    },
    {
      "key": "eventTitle",
      "value": "API Test Event",
      "type": "default",
      "enabled": true
    },
    {
      "key": "orderId",
      "value": "",
      "type": "default",
      "enabled": true
    },
    {
      "key": "ticketCode",
      "value": "POSTMAN-TICKET",
      "type": "default",
      "enabled": true
    },
    {
      "key": "notificationId",
      "value": "",
      "type": "default",
      "enabled": true
    },
    {
      "key": "budgetId",
      "value": "",
      "type": "default",
      "enabled": true
    },
    {
      "key": "expenseId",
      "value": "",
      "type": "default",
      "enabled": true
    },
    {
      "key": "cleanupEventId",
      "value": "",
      "type": "default",
      "enabled": true
    },
    {
      "key": "eventStartAt",
      "value": "2030-01-15T10:00:00",
      "type": "default",
      "enabled": true
    },
    {
      "key": "eventEndAt",
      "value": "2030-01-15T13:00:00",
      "type": "default",
      "enabled": true
    },
    {
      "key": "availabilityStartAt",
      "value": "2030-01-15T10:00:00Z",
      "type": "default",
      "enabled": true
    },
    {
      "key": "availabilityEndAt",
      "value": "2030-01-15T13:00:00Z",
      "type": "default",
      "enabled": true
    },
    {
      "key": "reportFrom",
      "value": "2024-01-01T00:00:00Z",
      "type": "default",
      "enabled": true
    },
    {
      "key": "reportTo",
      "value": "2031-01-01T00:00:00Z",
      "type": "default",
      "enabled": true
    },
    {
      "key": "resetToken",
      "value": "",
      "type": "secret",
      "enabled": true
    }
  ],
  "_postman_variable_scope": "environment",
  "_postman_exported_at": "2026-03-20T00:00:00.000Z",
  "_postman_exported_using": "Postman"
}
